Metadata-Version: 2.1
Name: streamjson
Version: 1.0.2
Summary: Send objects or arrays to a JSON file using a stream. Read objects from a JSON file using a stream.
Home-page: https://github.com/zaironjacobs/streamjson
Download-URL: https://github.com/zaironjacobs/streamjson/archive/v1.0.2.tar.gz
Author: Zairon Jacobs
Author-email: zaironjacobs@gmail.com
License: MIT
Keywords: json,stream,write,file,read,objects,arrays
Classifier: Development Status :: 5 - Production/Stable
Classifier: Intended Audience :: Developers
Classifier: License :: OSI Approved :: MIT License
Classifier: Operating System :: OS Independent
Classifier: Programming Language :: Python :: 3.9
Classifier: Natural Language :: English
Requires-Python: >=3
License-File: LICENSE
